odoo/addons/sale_partner_primeship/README.rst
odoo/addons/sale_partner_primeship/__init__.py
odoo/addons/sale_partner_primeship/__manifest__.py
odoo/addons/sale_partner_primeship/data/ir_cron.xml
odoo/addons/sale_partner_primeship/i18n/it.po
odoo/addons/sale_partner_primeship/i18n/sale_partner_primeship.pot
odoo/addons/sale_partner_primeship/models/__init__.py
odoo/addons/sale_partner_primeship/models/product_template.py
odoo/addons/sale_partner_primeship/models/res_partner.py
odoo/addons/sale_partner_primeship/models/sale_order.py
odoo/addons/sale_partner_primeship/models/sale_primeship.py
odoo/addons/sale_partner_primeship/readme/CONTRIBUTORS.md
odoo/addons/sale_partner_primeship/readme/DESCRIPTION.md
odoo/addons/sale_partner_primeship/readme/USAGE.md
odoo/addons/sale_partner_primeship/security/ir.model.access.csv
odoo/addons/sale_partner_primeship/security/sale_partner_primeship.xml
odoo/addons/sale_partner_primeship/static/description/icon.png
odoo/addons/sale_partner_primeship/static/description/index.html
odoo/addons/sale_partner_primeship/static/description/partner-with-primeship.png
odoo/addons/sale_partner_primeship/static/description/primeship-partner-view.png
odoo/addons/sale_partner_primeship/static/description/primeship-product.png
odoo/addons/sale_partner_primeship/tests/__init__.py
odoo/addons/sale_partner_primeship/tests/common.py
odoo/addons/sale_partner_primeship/tests/test_res_partner_primeship.py
odoo/addons/sale_partner_primeship/tests/test_sale_order_primeship.py
odoo/addons/sale_partner_primeship/tests/test_sale_primeship.py
odoo/addons/sale_partner_primeship/views/product_template_views.xml
odoo/addons/sale_partner_primeship/views/res_partner_views.xml
odoo/addons/sale_partner_primeship/views/sale_primeship_views.xml
odoo_addon_sale_partner_primeship-18.0.1.0.0.4.dist-info/METADATA
odoo_addon_sale_partner_primeship-18.0.1.0.0.4.dist-info/WHEEL
odoo_addon_sale_partner_primeship-18.0.1.0.0.4.dist-info/top_level.txt
odoo_addon_sale_partner_primeship-18.0.1.0.0.4.dist-info/RECORD
