Metadata-Version: 2.1
Name: odoo-addon-sale_partner_primeship
Version: 18.0.1.0.0.4
Requires-Python: >=3.10
Requires-Dist: odoo-addon-account_invoice_start_end_dates==18.0.*
Requires-Dist: odoo==18.0.*
Summary: Allow you to manage time limited prime memberships and prime membership activation products.
Home-page: https://github.com/OCA/sale-workflow
License: AGPL-3
Author: Akretion, Odoo Community Association (OCA)
Author-email: support@odoo-community.org
Classifier: Programming Language :: Python
Classifier: Framework :: Odoo
Classifier: Framework :: Odoo :: 18.0
Classifier: License :: OSI Approved :: GNU Affero General Public License v3
